newsly_mail/__init__.py
newsly_mail/newsletter_mail.py
newsly_mail-0.2.dist-info/METADATA
newsly_mail-0.2.dist-info/WHEEL
newsly_mail-0.2.dist-info/top_level.txt
newsly_mail-0.2.dist-info/RECORD
