Metadata-Version: 2.1
Name: newsly_mail
Version: 0.2
Summary: Send emails for a new Newsletter
Author: Harshvardhan Gupta
Author-email: hvg1021@gmail.com;
